cosyvoice/__init__.py
cosyvoice/bin/export_jit.py
cosyvoice/bin/export_onnx.py
cosyvoice/bin/inference.py
cosyvoice/bin/train.py
cosyvoice/cli/__init__.py
cosyvoice/cli/cosyvoice.py
cosyvoice/cli/frontend.py
cosyvoice/cli/model.py
cosyvoice/dataset/__init__.py
cosyvoice/dataset/dataset.py
cosyvoice/dataset/processor.py
cosyvoice/flow/__init__.py
cosyvoice/flow/decoder.py
cosyvoice/flow/flow.py
cosyvoice/flow/flow_matching.py
cosyvoice/flow/length_regulator.py
cosyvoice/hifigan/__init__.py
cosyvoice/hifigan/f0_predictor.py
cosyvoice/hifigan/generator.py
cosyvoice/llm/__init__.py
cosyvoice/llm/llm.py
cosyvoice/transformer/__init__.py
cosyvoice/transformer/activation.py
cosyvoice/transformer/attention.py
cosyvoice/transformer/convolution.py
cosyvoice/transformer/decoder.py
cosyvoice/transformer/decoder_layer.py
cosyvoice/transformer/embedding.py
cosyvoice/transformer/encoder.py
cosyvoice/transformer/encoder_layer.py
cosyvoice/transformer/label_smoothing_loss.py
cosyvoice/transformer/positionwise_feed_forward.py
cosyvoice/transformer/subsampling.py
cosyvoice/utils/__init__.py
cosyvoice/utils/class_utils.py
cosyvoice/utils/common.py
cosyvoice/utils/executor.py
cosyvoice/utils/file_utils.py
cosyvoice/utils/frontend_utils.py
cosyvoice/utils/mask.py
cosyvoice/utils/scheduler.py
cosyvoice/utils/train_utils.py
cosyvoice_package-0.0.3.dist-info/METADATA
cosyvoice_package-0.0.3.dist-info/WHEEL
cosyvoice_package-0.0.3.dist-info/top_level.txt
cosyvoice_package-0.0.3.dist-info/RECORD
