Metadata-Version: 2.1
Name: cosyvoice_package
Version: 0.0.3
Summary: cosyvoice package by xp
Author-email: xp <1426813058@qq.com>
Classifier: Programming Language :: Python :: 3
Classifier: License :: OSI Approved :: MIT License
Classifier: Operating System :: OS Independent
Requires-Python: >=3.8
Requires-Dist: hydra-core ==1.3.2
Requires-Dist: HyperPyYAML ==1.2.2
Requires-Dist: inflect ==7.3.1
Requires-Dist: librosa ==0.10.2
Requires-Dist: pyarrow ==17.0.0
Requires-Dist: omegaconf ==2.3.0
Requires-Dist: onnx ==1.16.0
Requires-Dist: onnxruntime ==1.16.0
Requires-Dist: openai-whisper ==20231117
Requires-Dist: soundfile ==0.12.1
Requires-Dist: WeTextProcessing ==1.0.3
Requires-Dist: matcha-tts-package ==0.0.3
Requires-Dist: pillow ==9.0.0
